Politics_and_Py/Config.py
Politics_and_Py/Core.py
Politics_and_Py/Exceptions.py
Politics_and_Py/Utils.py
Politics_and_Py/__init__.py
politics_and_py-0.1.0.dist-info/METADATA
politics_and_py-0.1.0.dist-info/WHEEL
politics_and_py-0.1.0.dist-info/licenses/LICENSE.md
politics_and_py-0.1.0.dist-info/RECORD
