Metadata-Version: 2.1
Name: Politics_and_Py
Version: 0.1.0
Summary: A package for managing Politics and War data
Project-URL: Homepage, https://github.com/Star-Tube/PnP
Project-URL: Bug Tracker, https://github.com/Star-Tube/PnP/issues
Author: Star_Tube
License-File: LICENSE.md
Classifier: License :: OSI Approved :: GNU General Public License v3 (GPLv3)
Classifier: Operating System :: OS Independent
Classifier: Programming Language :: Python :: 3
Requires-Python: >=3.10
